mog_excel_to_pdf/__init__.py
mog_excel_to_pdf/__main__.py
mog_excel_to_pdf-1.0.0.dist-info/METADATA
mog_excel_to_pdf-1.0.0.dist-info/WHEEL
mog_excel_to_pdf-1.0.0.dist-info/entry_points.txt
mog_excel_to_pdf-1.0.0.dist-info/licenses/LICENSE
mog_excel_to_pdf-1.0.0.dist-info/RECORD
