Metadata-Version: 2.4
Name: mog-excel-to-pdf
Version: 1.0.0
Summary: Excel の複数シートをグループ選択して PDF に出力するツール
Project-URL: Homepage, https://github.com/mogwai-dev/mog-excel-to-pdf
Project-URL: Repository, https://github.com/mogwai-dev/mog-excel-to-pdf
Project-URL: Issues, https://github.com/mogwai-dev/mog-excel-to-pdf/issues
Author: mogwai
License: MIT License
License-File: LICENSE
Keywords: COM,Excel,PDF,Windows,batch,convert,export,spreadsheet
Classifier: Development Status :: 4 - Beta
Classifier: Intended Audience :: Developers
Classifier: Intended Audience :: End Users/Desktop
Classifier: License :: OSI Approved :: MIT License
Classifier: Operating System :: Microsoft :: Windows
Classifier: Programming Language :: Python :: 3
Classifier: Programming Language :: Python :: 3.11
Classifier: Programming Language :: Python :: 3.12
Classifier: Programming Language :: Python :: 3.13
Classifier: Topic :: Office/Business
Classifier: Topic :: Utilities
Requires-Python: >=3.11
Requires-Dist: pypdf2>=3.0.1
Requires-Dist: pypdf>=4.0.0
Requires-Dist: pywin32>=311
